computer-organization-experiment/cpu.vhdl
library ieee;
use ieee.std_logic_1164.all;

package cru is
    subtype word is std_logic_vector(31 downto 0);
    constant clock_time : time := 10 ns;
end package;

library ieee;
use ieee.std_logic_1164.all;
use work.cru.all;

entity reg is
    port (
        CLK: in std_logic; -- Rising edge -> Read; Falling edge -> Write.
        W: in word; -- The data to write.
        ENABLE: in std_logic; -- If 1 then at falling edge of clock, W will be written.
        ZERO: in std_logic; -- If 1 then at rising edge of clock, 0 will be output to R.
        R: out word -- The data to read.
    );
end entity;

architecture Behavioral of reg is
    signal V: word := (others => '0');
begin
    process(CLK)
    begin
        if rising_edge(CLK) then
            if ZERO = '1' then
                R <= (others => '0');
            else
                R <= V;
            end if;
        end if;
        if falling_edge(CLK) and ENABLE = '1' then
            V <= W;
        end if;
    end process;
end architecture;

library ieee;
use ieee.std_logic_1164.all;
use ieee.numeric_std.all;
use ieee.std_logic_unsigned.all;
use work.cru.all;

entity register_file is
    port (
        CLK: in std_logic;
        ENABLE: in std_logic;
        R1, R2, W: in std_logic_vector(4 downto 0);
        WD: in std_logic_vector(31 downto 0);
        RD1, RD2: out std_logic_vector(31 downto 0)
    );
end entity;

architecture Behavioral of register_file is
    type reg_file_type is array (0 to 31) of std_logic_vector(31 downto 0);
    signal reg_file: reg_file_type := (others => (others => '0'));
begin
    process (CLK)
    begin
        if rising_edge(CLK) then
            RD1 <= reg_file(to_integer(unsigned(R1)));
            RD2 <= reg_file(to_integer(unsigned(R2)));
        end if;
        if falling_edge(CLK) and ENABLE = '1' then
            reg_file(to_integer(unsigned(W))) <= WD;
        end if;
    end process;
end architecture;

library ieee;
use ieee.std_logic_1164.all;
use ieee.numeric_std.all;
use ieee.std_logic_unsigned.all;
use work.cru.all;

entity alu is
    port (
        A, B: in std_logic_vector(31 downto 0);
        ALUC: in std_logic_vector(3 downto 0);
        S: out std_logic_vector(31 downto 0);
        Z: out std_logic
    );
end entity;

architecture Behavioral of alu is
begin
    S <= A + B when ALUC(2 downto 0) ?= B"000"
         else A - B when ALUC(2 downto 0) ?= B"010"
         else A and B when ALUC(2 downto 0) ?= B"100"
         else A or B when ALUC(2 downto 0) ?= B"101"
         else A xor B when ALUC(2 downto 0) ?= B"110"
         else std_logic_vector(signed(A) sll 16) and X"FFFF0000" when ALUC(2 downto 0) ?= B"110"
         else std_logic_vector(signed(A) sll to_integer(unsigned(B))) when ALUC ?= B"0011"
         else std_logic_vector(signed(A) srl to_integer(unsigned(B))) when ALUC ?= B"0111"
         else std_logic_vector(signed(A) sra to_integer(unsigned(B))) when ALUC ?= B"1111";
    Z <= S ?= X"00000000";
end architecture;

library ieee;
use ieee.std_logic_1164.all;
use ieee.numeric_std.all;
use ieee.std_logic_unsigned.all;
use work.cru.all;

entity clock is
    port(CLK: out std_logic);
end entity;

architecture Behavioral of clock is
    signal V: std_logic := '0';
begin
    V <= not V after clock_time;
    CLK <= V;
end architecture;

library ieee;
use ieee.std_logic_1164.all;
use ieee.numeric_std.all;
use ieee.std_logic_unsigned.all;
use work.cru.all;

entity ram is
    port(CLK: in std_logic;
        D: inout word;
        ADDR: in word;
        ENABLE: in std_logic
    );
end entity;

architecture Behavioral of ram is
    type memory_type is array (0 to 16#30#) of word;
    signal memory: memory_type;
    signal V: std_logic := '0';
begin
    init: process is
    begin
        memory(0 to 16#1F#) <= ( 
            X"3c010000",
            X"34240020",
            X"20050004",
            X"0c000018",
            X"ac820000",
            X"8c890000",
            X"01244022",
            X"20050003",
            X"20a5ffff",
            X"34a8ffff",
            X"39085555",
            X"2009ffff",
            X"312affff",
            X"01493025",
            X"01494026",
            X"01463824",
            X"10a00001",
            X"08000008",
            X"2005ffff",
            X"000543c0",
            X"00084400",
            X"00084403",
            X"000843c2",
            X"08000017",
            X"00004020",
            X"8c890000",
            X"20840004",
            X"01094020",
            X"20a5ffff",
            X"14a0fffb",
            X"00081000",
            X"03e00008"
        );
        memory(16#20# to 16#20# + 3) <= (
            X"000000A3",
            X"00000027",
            X"00000079",
            X"00000115"
        );
        wait;
    end process;
    b: process(CLK) is 
    begin
        if rising_edge(CLK) then
            D <= memory(to_integer(unsigned(ADDR)));
        end if;
        if falling_edge(CLK) and ENABLE = '1' then
            memory(to_integer(unsigned(ADDR))) <= D;
        end if;
    end process;
end architecture;

library ieee;
use ieee.std_logic_1164.all;
use ieee.numeric_std.all;
use ieee.std_logic_unsigned.all;
use work.cru.all;

entity cpu is
    port (
        CLK: in std_logic
    );
end entity;

architecture Behavioral of cpu is
    signal pc: word := X"00000000";
    signal pc_to_write: word;

    signal ins: word;

    signal enable_mem: std_logic;
    signal write_mem: std_logic := '0';
    signal addr: word := X"00000000";
    signal mem_value: word;

    signal WRITE_REG: std_logic := '0';
    signal R1: std_logic_vector(4 downto 0) := B"00000";
    signal R2: std_logic_vector(4 downto 0)  := B"00000";
    signal W: std_logic_vector(4 downto 0)  := B"00000";
    signal WD: std_logic_vector(31 downto 0);
    signal RD1: std_logic_vector(31 downto 0) := X"00000000";
    signal RD2: std_logic_vector(31 downto 0) := X"00000000";

    signal A: std_logic_vector(31 downto 0) := X"00000000";
    signal B: std_logic_vector(31 downto 0) := X"00000000";
    signal ALUC: std_logic_vector(3 downto 0) := B"0000";
    signal S: std_logic_vector(31 downto 0);
    signal Z: std_logic;
begin
    pc_reg: entity work.reg
        port map (
            CLK => CLK,
            ENABLE => '1',
            ZERO => '0',
            W => pc_to_write,
            R => pc
        );
    reg: entity work.register_file
        port map(
            CLK => CLK,
            ENABLE => WRITE_REG,
            R1 => R1,
            R2 => R2,
            W => W,
            WD => WD,
            RD1 => RD1,
            RD2 => RD2
        );
    alu: entity work.alu
        port map(
            A => A,
            B => B,
            ALUC => ALUC,
            S => S,
            Z => Z
        );

    ram: entity work.ram
        port map (
            CLK => CLK,
            D => mem_value,
            ADDR => addr,
            ENABLE => write_mem
        );

    logic: process is
    begin
        wait until rising_edge(CLK);
        wait for 100 ps;

        addr <= pc;
        wait for 1 ns;
        ins <= mem_value;
        pc_to_write <= pc + 1;

        WRITE_REG <= '0';

        if ins(31 downto 27) ?= B"00001" then -- j / jal
            if ins(26) = '1' then -- jal
                W <= B"11111";
                WD <= pc;
                WRITE_REG <= '1';
            end if;
            pc_to_write <= (25 downto 0 => ins(25 downto 0), others => '0');
        elsif ins(31 downto 26) = B"000000" then
            if ins(5) = '1' then
                R1 <= ins(25 downto 21);
                R2 <= ins(20 downto 16);
                ALUC <= ins(3 downto 0);
                A <= RD1;
                B <= RD2;
                W <= ins(15 downto 11);
                WRITE_REG <= '1';
                WD <= S;
            elsif ins(3) = '0' then
                R1 <= ins(20 downto 16);
                ALUC(3 downto 2) <= ins(1 downto 0);
                ALUC(1 downto 0) <= B"11";
                A <= RD1;
                B <= (4 downto 0 => ins(10 downto 6), others => '0');
                W <= ins(15 downto 11);
                WRITE_REG <= '1';
                WD <= S;
            else
                R1 <= ins(25 downto 21);
                WRITE_REG <= '0';
                pc_to_write <= RD1;
            end if;
        else
            if ins(31) = '1' then
                enable_mem <= '1';
                R1 <= ins(25 downto 21);
                ALUC <= B"0000";
                A <= RD1;
                B <= (15 downto 0 => ins(15 downto 0), others => '0' );
                if ins(29) = '1' then
                    W <= ins(20 downto 16);
                    write_mem <= '0';
                else
                    R2 <= ins(20 downto 16);
                    write_mem <= '1';
                end if;
            elsif ins(29 downto 26) = B"1111" then
                WRITE_REG <= '1';
                W <= ins(20 downto 16);
                WD(31 downto 16) <= ins(15 downto 0);
            elsif ins(29) = '1' then
                R1 <= ins(25 downto 21);
                ALUC <= ins(29 downto 26);
                A <= RD1;
                B(15 downto 0) <= ins(15 downto 0);
                B(31 downto 16) <= X"0000";
                W <= ins(20 downto 16);
                WRITE_REG <= '1';
                WD <= S;
            else
                R1 <= ins(25 downto 21);
                R2 <= ins(20 downto 16);
                ALUC <= B"0010";
                A <= RD1;
                B <= RD2;
                if Z = '1' then
                    pc_to_write <= pc_to_write + ins(15 downto 0);
                end if;
                WRITE_REG <= '0';
            end if;
        end if;

        if enable_mem then
            if write_mem then
                WRITE_REG <= '0';
                mem_value <= RD2;
            else
                WRITE_REG <= '1';
                WD <= mem_value;
            end if;
        else
            write_mem <= '0';
        end if;
    end process;
end architecture;

library ieee;
use ieee.std_logic_1164.all;
use ieee.numeric_std.all;
use ieee.std_logic_unsigned.all;
use work.cru.all;

entity cpu_test_bench is
end entity;

architecture Behavioral of cpu_test_bench is
    signal CLK: std_logic;
begin
    clock: entity work.clock
        port map (
            CLK
        );
    cpu : entity work.cpu
        port map (
            CLK
        );
end architecture;

computer-organization-experiment/out.vcd
$date
  Sat Dec 25 14:07:37 2021
$end
$version
  GHDL v0
$end
$timescale
  1 fs
$end
$scope module standard $end
$upscope $end
$scope module textio $end
$upscope $end
$scope module std_logic_1164 $end
$upscope $end
$scope module numeric_std $end
$upscope $end
$scope module std_logic_arith $end
$upscope $end
$scope module std_logic_unsigned $end
$upscope $end
$scope module cru $end
$upscope $end
$scope module cpu_test_bench $end
$var reg 1 ! clk $end
$scope module clock $end
$var reg 1 " clk $end
$var reg 1 # v $end
$upscope $end
$scope module cpu $end
$var reg 1 $ clk $end
$var reg 32 % pc[31:0] $end
$var reg 32 & pc_to_write[31:0] $end
$var reg 32 ' ins[31:0] $end
$var reg 1 ( enable_mem $end
$var reg 1 ) write_mem $end
$var reg 32 * addr[31:0] $end
$var reg 32 + mem_value[31:0] $end
$var reg 1 , write_reg $end
$var reg 5 - r1[4:0] $end
$var reg 5 . r2[4:0] $end
$var reg 5 / w[4:0] $end
$var reg 32 0 wd[31:0] $end
$var reg 32 1 rd1[31:0] $end
$var reg 32 2 rd2[31:0] $end
$var reg 32 3 a[31:0] $end
$var reg 32 4 b[31:0] $end
$var reg 4 5 aluc[3:0] $end
$var reg 32 6 s[31:0] $end
$var reg 1 7 z $end
$scope module pc_reg $end
$var reg 1 8 clk $end
$var reg 32 9 w[31:0] $end
$var reg 1 : enable $end
$var reg 1 ; zero $end
$var reg 32 < r[31:0] $end
$var reg 32 = v[31:0] $end
$upscope $end
$scope module reg $end
$var reg 1 > clk $end
$var reg 1 ? enable $end
$var reg 5 @ r1[4:0] $end
$var reg 5 A r2[4:0] $end
$var reg 5 B w[4:0] $end
$var reg 32 C wd[31:0] $end
$var reg 32 D rd1[31:0] $end
$var reg 32 E rd2[31:0] $end
$comment reg_file is not handled $end
$upscope $end
$scope module alu $end
$var reg 32 F a[31:0] $end
$var reg 32 G b[31:0] $end
$var reg 4 H aluc[3:0] $end
$var reg 32 I s[31:0] $end
$var reg 1 J z $end
$upscope $end
$scope module ram $end
$var reg 1 K clk $end
$var reg 32 L d[31:0] $end
$var reg 32 M addr[31:0] $end
$var reg 1 N enable $end
$comment data is not handled $end
$var reg 1 O v $end
$upscope $end
$upscope $end
$upscope $end
$enddefinitions $end
#0
0!
0"
0#
0$
bUUUUUUUUUUUUUUUUUUUUUUUUUUUUUUUU %
bUUUUUUUUUUUUUUUUUUUUUUUUUUUUUUUU &
bUUUUUUUUUUUUUUUUUUUUUUUUUUUUUUUU '
U(
0)
b00000000000000000000000000000000 *
bUUUUUUUUUUUUUUUUUUUUUUUUUUUUUUUU +
0,
b00000 -
b00000 .
b00000 /
bUUUUUUUUUUUUUUUUUUUUUUUUUUUUUUUU 0
bUUUUUUUUUUUUUUUUUUUUUUUUUUUUUUUU 1
bUUUUUUUUUUUUUUUUUUUUUUUUUUUUUUUU 2
b00000000000000000000000000000000 3
b00000000000000000000000000000000 4
b0000 5
b00000000000000000000000000000000 6
17
08
bUUUUUUUUUUUUUUUUUUUUUUUUUUUUUUUU 9
1:
0;
bUUUUUUUUUUUUUUUUUUUUUUUUUUUUUUUU <
b00000000000000000000000000000000 =
0>
0?
b00000 @
b00000 A
b00000 B
bUUUUUUUUUUUUUUUUUUUUUUUUUUUUUUUU C
bUUUUUUUUUUUUUUUUUUUUUUUUUUUUUUUU D
bUUUUUUUUUUUUUUUUUUUUUUUUUUUUUUUU E
b00000000000000000000000000000000 F
b00000000000000000000000000000000 G
b0000 H
b00000000000000000000000000000000 I
1J
0K
bUUUUUUUUUUUUUUUUUUUUUUUUUUUUUUUU L
b00000000000000000000000000000000 M
0N
0O
#10000000
1!
1"
1#
1$
b00000000000000000000000000000000 %
b00000000000000000000000000000000 1
b00000000000000000000000000000000 2
18
b00000000000000000000000000000000 <
1>
b00000000000000000000000000000000 D
b00000000000000000000000000000000 E
1K
#10100000
#11100000
bXXXXXXXXXXXXXXXXXXXXXXXXXXXXXXXX &
bUUUUU -
bUUUUU .
b0010 5
bXXXXXXXXXXXXXXXXXXXXXXXXXXXXXXXX 9
bUUUUU @
bUUUUU A
b0010 H
#20000000
0!
0"
0#
0$
08
bXXXXXXXXXXXXXXXXXXXXXXXXXXXXXXXX =
0>
0K
#30000000
1!
1"
1#
1$
bXXXXXXXXXXXXXXXXXXXXXXXXXXXXXXXX %
18
bXXXXXXXXXXXXXXXXXXXXXXXXXXXXXXXX <
1>
1K
#30100000
bXXXXXXXXXXXXXXXXXXXXXXXXXXXXXXXX *
bXXXXXXXXXXXXXXXXXXXXXXXXXXXXXXXX M
#31100000
#40000000
0!
0"
0#
0$
08
0>
0K
#50000000
1!
1"
1#
1$
18
1>
1K
#50100000
#51100000
#60000000
0!
0"
0#
0$
08
0>
0K
#70000000
1!
1"
1#
1$
18
1>
1K
#70100000
#71100000
#80000000
0!
0"
0#
0$
08
0>
0K
#90000000
1!
1"
1#
1$
18
1>
1K
#90100000
#91100000
#100000000
0!
0"
0#
0$
08
0>
0K
#110000000
1!
1"
1#
1$
18
1>
1K
#110100000
#111100000
#120000000
0!
0"
0#
0$
08
0>
0K
#130000000
1!
1"
1#
1$
18
1>
1K
#130100000
#131100000
#140000000
0!
0"
0#
0$
08
0>
0K
#150000000
1!
1"
1#
1$
18
1>
1K
#150100000
#151100000
#160000000
0!
0"
0#
0$
08
0>
0K
#170000000
1!
1"
1#
1$
18
1>
1K
#170100000
#171100000
#180000000
0!
0"
0#
0$
08
0>
0K
#190000000
1!
1"
1#
1$
18
1>
1K
#190100000
#191100000
#200000000
0!
0"
0#
0$
08
0>
0K
#210000000
1!
1"
1#
1$
18
1>
1K
#210100000
#211100000
#220000000
0!
0"
0#
0$
08
0>
0K
#230000000
1!
1"
1#
1$
18
1>
1K
#230100000
#231100000
#240000000
0!
0"
0#
0$
08
0>
0K
#250000000
1!
1"
1#
1$
18
1>
1K
#250100000
#251100000
#260000000
0!
0"
0#
0$
08
0>
0K
#270000000
1!
1"
1#
1$
18
1>
1K
#270100000
#271100000
#280000000
0!
0"
0#
0$
08
0>
0K
#290000000
1!
1"
1#
1$
18
1>
1K
#290100000
#291100000
#300000000
0!
0"
0#
0$
08
0>
0K
#310000000
1!
1"
1#
1$
18
1>
1K
#310100000
#311100000
#320000000
0!
0"
0#
0$
08
0>
0K
#330000000
1!
1"
1#
1$
18
1>
1K
#330100000
#331100000
#340000000
0!
0"
0#
0$
08
0>
0K
#350000000
1!
1"
1#
1$
18
1>
1K
#350100000
#351100000
#360000000
0!
0"
0#
0$
08
0>
0K
#370000000
1!
1"
1#
1$
18
1>
1K
#370100000
#371100000
#380000000
0!
0"
0#
0$
08
0>
0K
#390000000
1!
1"
1#
1$
18
1>
1K
#390100000
#391100000
#400000000
0!
0"
0#
0$
08
0>
0K
#410000000
1!
1"
1#
1$
18
1>
1K
#410100000
#411100000
#420000000
0!
0"
0#
0$
08
0>
0K
#430000000
1!
1"
1#
1$
18
1>
1K
#430100000
#431100000
#440000000
0!
0"
0#
0$
08
0>
0K
#450000000
1!
1"
1#
1$
18
1>
1K
#450100000
#451100000
#460000000
0!
0"
0#
0$
08
0>
0K
#470000000
1!
1"
1#
1$
18
1>
1K
#470100000
#471100000
#480000000
0!
0"
0#
0$
08
0>
0K
#490000000
1!
1"
1#
1$
18
1>
1K
#490100000
#491100000
#500000000
0!
0"
0#
0$
08
0>
0K
#510000000
1!
1"
1#
1$
18
1>
1K
#510100000
#511100000
#520000000
0!
0"
0#
0$
08
0>
0K
#530000000
1!
1"
1#
1$
18
1>
1K
#530100000
#531100000
#540000000
0!
0"
0#
0$
08
0>
0K
#550000000
1!
1"
1#
1$
18
1>
1K
#550100000
#551100000
#560000000
0!
0"
0#
0$
08
0>
0K
#570000000
1!
1"
1#
1$
18
1>
1K
#570100000
#571100000
#580000000
0!
0"
0#
0$
08
0>
0K
#590000000
1!
1"
1#
1$
18
1>
1K
#590100000
#591100000
#600000000
0!
0"
0#
0$
08
0>
0K
#610000000
1!
1"
1#
1$
18
1>
1K
#610100000
#611100000
#620000000
0!
0"
0#
0$
08
0>
0K
#630000000
1!
1"
1#
1$
18
1>
1K
#630100000
#631100000
#640000000
0!
0"
0#
0$
08
0>
0K
#650000000
1!
1"
1#
1$
18
1>
1K
#650100000
#651100000
#660000000
0!
0"
0#
0$
08
0>
0K
#670000000
1!
1"
1#
1$
18
1>
1K
#670100000
#671100000
#680000000
0!
0"
0#
0$
08
0>
0K
#690000000
1!
1"
1#
1$
18
1>
1K
#690100000
#691100000
#700000000
0!
0"
0#
0$
08
0>
0K
#710000000
1!
1"
1#
1$
18
1>
1K
#710100000
#711100000
#720000000
0!
0"
0#
0$
08
0>
0K
#730000000
1!
1"
1#
1$
18
1>
1K
#730100000
#731100000
#740000000
0!
0"
0#
0$
08
0>
0K
#750000000
1!
1"
1#
1$
18
1>
1K
#750100000
#751100000
#760000000
0!
0"
0#
0$
08
0>
0K
#770000000
1!
1"
1#
1$
18
1>
1K
#770100000
#771100000
#780000000
0!
0"
0#
0$
08
0>
0K
#790000000
1!
1"
1#
1$
18
1>
1K
#790100000
#791100000
#800000000
0!
0"
0#
0$
08
0>
0K
#810000000
1!
1"
1#
1$
18
1>
1K
#810100000
#811100000
#820000000
0!
0"
0#
0$
08
0>
0K
#830000000
1!
1"
1#
1$
18
1>
1K
#830100000
#831100000
#840000000
0!
0"
0#
0$
08
0>
0K
#850000000
1!
1"
1#
1$
18
1>
1K
#850100000
#851100000
#860000000
0!
0"
0#
0$
08
0>
0K
#870000000
1!
1"
1#
1$
18
1>
1K
#870100000
#871100000
#880000000
0!
0"
0#
0$
08
0>
0K
#890000000
1!
1"
1#
1$
18
1>
1K
#890100000
#891100000
#900000000
0!
0"
0#
0$
08
0>
0K
#910000000
1!
1"
1#
1$
18
1>
1K
#910100000
#911100000
#920000000
0!
0"
0#
0$
08
0>
0K
#930000000
1!
1"
1#
1$
18
1>
1K
#930100000
#931100000
#940000000
0!
0"
0#
0$
08
0>
0K
#950000000
1!
1"
1#
1$
18
1>
1K
#950100000
#951100000
#960000000
0!
0"
0#
0$
08
0>
0K
#970000000
1!
1"
1#
1$
18
1>
1K
#970100000
#971100000
#980000000
0!
0"
0#
0$
08
0>
0K
#990000000
1!
1"
1#
1$
18
1>
1K
#990100000
#991100000
#1000000000
0!
0"
0#
0$
08
0>
0K
#1010000000
1!
1"
1#
1$
18
1>
1K
#1010100000
#1011100000
#1020000000
0!
0"
0#
0$
08
0>
0K
#1030000000
1!
1"
1#
1$
18
1>
1K
#1030100000
#1031100000
#1040000000
0!
0"
0#
0$
08
0>
0K
#1050000000
1!
1"
1#
1$
18
1>
1K
#1050100000
#1051100000
#1060000000
0!
0"
0#
0$
08
0>
0K
#1070000000
1!
1"
1#
1$
18
1>
1K
#1070100000
#1071100000
#1080000000
0!
0"
0#
0$
08
0>
0K
#1090000000
1!
1"
1#
1$
18
1>
1K
#1090100000
#1091100000
#1100000000
0!
0"
0#
0$
08
0>
0K
#1110000000
1!
1"
1#
1$
18
1>
1K
#1110100000
#1111100000
#1120000000
0!
0"
0#
0$
08
0>
0K
#1130000000
1!
1"
1#
1$
18
1>
1K
#1130100000
#1131100000
#1140000000
0!
0"
0#
0$
08
0>
0K
#1150000000
1!
1"
1#
1$
18
1>
1K
#1150100000
#1151100000
#1160000000
0!
0"
0#
0$
08
0>
0K
#1170000000
1!
1"
1#
1$
18
1>
1K
#1170100000
#1171100000
#1180000000
0!
0"
0#
0$
08
0>
0K
#1190000000
1!
1"
1#
1$
18
1>
1K
#1190100000
#1191100000
#1200000000
0!
0"
0#
0$
08
0>
0K
#1210000000
1!
1"
1#
1$
18
1>
1K
#1210100000
#1211100000
#1220000000
0!
0"
0#
0$
08
0>
0K
#1230000000
1!
1"
1#
1$
18
1>
1K
#1230100000
#1231100000
#1240000000
0!
0"
0#
0$
08
0>
0K
#1250000000
1!
1"
1#
1$
18
1>
1K
#1250100000
#1251100000
#1260000000
0!
0"
0#
0$
08
0>
0K
#1270000000
1!
1"
1#
1$
18
1>
1K
#1270100000
#1271100000
#1280000000
0!
0"
0#
0$
08
0>
0K
#1290000000
1!
1"
1#
1$
18
1>
1K
#1290100000
#1291100000
#1300000000
0!
0"
0#
0$
08
0>
0K
#1310000000
1!
1"
1#
1$
18
1>
1K
#1310100000
#1311100000
#1320000000
0!
0"
0#
0$
08
0>
0K
#1330000000
1!
1"
1#
1$
18
1>
1K
#1330100000
#1331100000
#1340000000
0!
0"
0#
0$
08
0>
0K
#1350000000
1!
1"
1#
1$
18
1>
1K
#1350100000
#1351100000
#1360000000
0!
0"
0#
0$
08
0>
0K
#1370000000
1!
1"
1#
1$
18
1>
1K
#1370100000
#1371100000
#1380000000
0!
0"
0#
0$
08
0>
0K
#1390000000
1!
1"
1#
1$
18
1>
1K
#1390100000
#1391100000
#1400000000
0!
0"
0#
0$
08
0>
0K
#1410000000
1!
1"
1#
1$
18
1>
1K
#1410100000
#1411100000
#1420000000
0!
0"
0#
0$
08
0>
0K
#1430000000
1!
1"
1#
1$
18
1>
1K
#1430100000
#1431100000
#1440000000
0!
0"
0#
0$
08
0>
0K
#1450000000
1!
1"
1#
1$
18
1>
1K
#1450100000
#1451100000
#1460000000
0!
0"
0#
0$
08
0>
0K
#1470000000
1!
1"
1#
1$
18
1>
1K
#1470100000
#1471100000
#1480000000
0!
0"
0#
0$
08
0>
0K
#1490000000
1!
1"
1#
1$
18
1>
1K
#1490100000
#1491100000
#1500000000
0!
0"
0#
0$
08
0>
0K
#1510000000
1!
1"
1#
1$
18
1>
1K
#1510100000
#1511100000
#1520000000
0!
0"
0#
0$
08
0>
0K
#1530000000
1!
1"
1#
1$
18
1>
1K
#1530100000
#1531100000
#1540000000
0!
0"
0#
0$
08
0>
0K
#1550000000
1!
1"
1#
1$
18
1>
1K
#1550100000
#1551100000
#1560000000
0!
0"
0#
0$
08
0>
0K
#1570000000
1!
1"
1#
1$
18
1>
1K
#1570100000
#1571100000
#1580000000
0!
0"
0#
0$
08
0>
0K
#1590000000
1!
1"
1#
1$
18
1>
1K
#1590100000
#1591100000
#1600000000
0!
0"
0#
0$
08
0>
0K
#1610000000
1!
1"
1#
1$
18
1>
1K
#1610100000
#1611100000
#1620000000
0!
0"
0#
0$
08
0>
0K
#1630000000
1!
1"
1#
1$
18
1>
1K
#1630100000
#1631100000
#1640000000
0!
0"
0#
0$
08
0>
0K
#1650000000
1!
1"
1#
1$
18
1>
1K
#1650100000
#1651100000
#1660000000
0!
0"
0#
0$
08
0>
0K
#1670000000
1!
1"
1#
1$
18
1>
1K
#1670100000
#1671100000
#1680000000
0!
0"
0#
0$
08
0>
0K
#1690000000
1!
1"
1#
1$
18
1>
1K
#1690100000
#1691100000
#1700000000
0!
0"
0#
0$
08
0>
0K
#1710000000
1!
1"
1#
1$
18
1>
1K
#1710100000
#1711100000
#1720000000
0!
0"
0#
0$
08
0>
0K
#1730000000
1!
1"
1#
1$
18
1>
1K
#1730100000
#1731100000
#1740000000
0!
0"
0#
0$
08
0>
0K
#1750000000
1!
1"
1#
1$
18
1>
1K
#1750100000
#1751100000
#1760000000
0!
0"
0#
0$
08
0>
0K
#1770000000
1!
1"
1#
1$
18
1>
1K
#1770100000
#1771100000
#1780000000
0!
0"
0#
0$
08
0>
0K
#1790000000
1!
1"
1#
1$
18
1>
1K
#1790100000
#1791100000
#1800000000
0!
0"
0#
0$
08
0>
0K
#1810000000
1!
1"
1#
1$
18
1>
1K
#1810100000
#1811100000
#1820000000
0!
0"
0#
0$
08
0>
0K
#1830000000
1!
1"
1#
1$
18
1>
1K
#1830100000
#1831100000
#1840000000
0!
0"
0#
0$
08
0>
0K
#1850000000
1!
1"
1#
1$
18
1>
1K
#1850100000
#1851100000
#1860000000
0!
0"
0#
0$
08
0>
0K
#1870000000
1!
1"
1#
1$
18
1>
1K
#1870100000
#1871100000
#1880000000
0!
0"
0#
0$
08
0>
0K
#1890000000
1!
1"
1#
1$
18
1>
1K
#1890100000
#1891100000
#1900000000
0!
0"
0#
0$
08
0>
0K
#1910000000
1!
1"
1#
1$
18
1>
1K
#1910100000
#1911100000
#1920000000
0!
0"
0#
0$
08
0>
0K
#1930000000
1!
1"
1#
1$
18
1>
1K
#1930100000
#1931100000
#1940000000
0!
0"
0#
0$
08
0>
0K
#1950000000
1!
1"
1#
1$
18
1>
1K
#1950100000
#1951100000
#1960000000
0!
0"
0#
0$
08
0>
0K
#1970000000
1!
1"
1#
1$
18
1>
1K
#1970100000
#1971100000
#1980000000
0!
0"
0#
0$
08
0>
0K
#1990000000
1!
1"
1#
1$
18
1>
1K
#1990100000
#1991100000
#2000000000
0!
0"
0#
0$
08
0>
0K
#2010000000
1!
1"
1#
1$
18
1>
1K
#2010100000
#2011100000
#2020000000
0!
0"
0#
0$
08
0>
0K
#2030000000
1!
1"
1#
1$
18
1>
1K
#2030100000
#2031100000
#2040000000
0!
0"
0#
0$
08
0>
0K
#2050000000
1!
1"
1#
1$
18
1>
1K
#2050100000
#2051100000
#2060000000
0!
0"
0#
0$
08
0>
0K
#2070000000
1!
1"
1#
1$
18
1>
1K
#2070100000
#2071100000
#2080000000
0!
0"
0#
0$
08
0>
0K
#2090000000
1!
1"
1#
1$
18
1>
1K
#2090100000
#2091100000
#2100000000
0!
0"
0#
0$
08
0>
0K
#2110000000
1!
1"
1#
1$
18
1>
1K
#2110100000
#2111100000
#2120000000
0!
0"
0#
0$
08
0>
0K
#2130000000
1!
1"
1#
1$
18
1>
1K
#2130100000
#2131100000
#2140000000
0!
0"
0#
0$
08
0>
0K
#2150000000
1!
1"
1#
1$
18
1>
1K
#2150100000
#2151100000
#2160000000
0!
0"
0#
0$
08
0>
0K
#2170000000
1!
1"
1#
1$
18
1>
1K
#2170100000
#2171100000
#2180000000
0!
0"
0#
0$
08
0>
0K
#2190000000
1!
1"
1#
1$
18
1>
1K
#2190100000
#2191100000
#2200000000
0!
0"
0#
0$
08
0>
0K
#2210000000
1!
1"
1#
1$
18
1>
1K
#2210100000
#2211100000
#2220000000
0!
0"
0#
0$
08
0>
0K
#2230000000
1!
1"
1#
1$
18
1>
1K
#2230100000
#2231100000
#2240000000
0!
0"
0#
0$
08
0>
0K
#2250000000
1!
1"
1#
1$
18
1>
1K
#2250100000
#2251100000
#2260000000
0!
0"
0#
0$
08
0>
0K
#2270000000
1!
1"
1#
1$
18
1>
1K
#2270100000
#2271100000
#2280000000
0!
0"
0#
0$
08
0>
0K
#2290000000
1!
1"
1#
1$
18
1>
1K
#2290100000
#2291100000
#2300000000
0!
0"
0#
0$
08
0>
0K
#2310000000
1!
1"
1#
1$
18
1>
1K
#2310100000
#2311100000
#2320000000
0!
0"
0#
0$
08
0>
0K
#2330000000
1!
1"
1#
1$
18
1>
1K
#2330100000
#2331100000
#2340000000
0!
0"
0#
0$
08
0>
0K
#2350000000
1!
1"
1#
1$
18
1>
1K
#2350100000
#2351100000
#2360000000
0!
0"
0#
0$
08
0>
0K
#2370000000
1!
1"
1#
1$
18
1>
1K
#2370100000
#2371100000
#2380000000
0!
0"
0#
0$
08
0>
0K
#2390000000
1!
1"
1#
1$
18
1>
1K
#2390100000
#2391100000
#2400000000
0!
0"
0#
0$
08
0>
0K
#2410000000
1!
1"
1#
1$
18
1>
1K
#2410100000
#2411100000
#2420000000
0!
0"
0#
0$
08
0>
0K
#2430000000
1!
1"
1#
1$
18
1>
1K
#2430100000
#2431100000
#2440000000
0!
0"
0#
0$
08
0>
0K
#2450000000
1!
1"
1#
1$
18
1>
1K
#2450100000
#2451100000
#2460000000
0!
0"
0#
0$
08
0>
0K
#2470000000
1!
1"
1#
1$
18
1>
1K
#2470100000
#2471100000
#2480000000
0!
0"
0#
0$
08
0>
0K
#2490000000
1!
1"
1#
1$
18
1>
1K
#2490100000
#2491100000
#2500000000
0!
0"
0#
0$
08
0>
0K
#2510000000
1!
1"
1#
1$
18
1>
1K
#2510100000
#2511100000
#2520000000
0!
0"
0#
0$
08
0>
0K
#2530000000
1!
1"
1#
1$
18
1>
1K
#2530100000
#2531100000
#2540000000
0!
0"
0#
0$
08
0>
0K
#2550000000
1!
1"
1#
1$
18
1>
1K
#2550100000
#2551100000
#2560000000
0!
0"
0#
0$
08
0>
0K
#2570000000
1!
1"
1#
1$
18
1>
1K
#2570100000
#2571100000
#2580000000
0!
0"
0#
0$
08
0>
0K
#2590000000
1!
1"
1#
1$
18
1>
1K
#2590100000
#2591100000
#2600000000
0!
0"
0#
0$
08
0>
0K
#2610000000
1!
1"
1#
1$
18
1>
1K
#2610100000
#2611100000
#2620000000
0!
0"
0#
0$
08
0>
0K
#2630000000
1!
1"
1#
1$
18
1>
1K
#2630100000
#2631100000
#2640000000
0!
0"
0#
0$
08
0>
0K
#2650000000
1!
1"
1#
1$
18
1>
1K
#2650100000
#2651100000
#2660000000
0!
0"
0#
0$
08
0>
0K
#2670000000
1!
1"
1#
1$
18
1>
1K
#2670100000
#2671100000
#2680000000
0!
0"
0#
0$
08
0>
0K
#2690000000
1!
1"
1#
1$
18
1>
1K
#2690100000
#2691100000
#2700000000
0!
0"
0#
0$
08
0>
0K
